{"cities":[{"name":"Aberdeen","zips":["28315"]},{"name":"Advance","zips":["27006"]},{"name":"Ahoskie","zips":["27910"]},{"name":"Alamance","zips":["27201"]},{"name":"Albemarle","zips":["28001","28002"]},{"name":"Albertson","zips":["28508"]},{"name":"Alexander","zips":["28701"]},{"name":"Alexis","zips":["28006"]},{"name":"Alliance","zips":["28509"]},{"name":"Almond","zips":["28702"]},{"name":"Altamahaw","zips":["27202"]},{"name":"Andrews","zips":["28901"]},{"name":"Angier","zips":["27501"]},{"name":"Ansonville","zips":["28007"]},{"name":"Apex","zips":["27502","27523","27539"]},{"name":"Arapahoe","zips":["28510"]},{"name":"Ararat","zips":["27007"]},{"name":"Arden","zips":["28704"]},{"name":"Ash","zips":["28420"]},{"name":"Asheboro","zips":["27203","27204","27205"]},{"name":"Asheville","zips":["28801","28802","28803","28804","28805","28806","28810","28813","28814","28815","28816"]},{"name":"Atkinson","zips":["28421"]},{"name":"Atlantic","zips":["28511"]},{"name":"Atlantic Beach","zips":["28512"]},{"name":"Aulander","zips":["27805"]},{"name":"Aurora","zips":["27806"]},{"name":"Autryville","zips":["28318"]},{"name":"Avon","zips":["27915"]},{"name":"Ayden","zips":["28513"]},{"name":"Aydlett","zips":["27916"]},{"name":"Badin","zips":["28009"]},{"name":"Bahama","zips":["27503"]},{"name":"Bailey","zips":["27807"]},{"name":"Bakersville","zips":["28705"]},{"name":"Balsam","zips":["28707"]},{"name":"Balsam Grove","zips":["28708"]},{"name":"Banner Elk","zips":["28604"]},{"name":"Barco","zips":["27917"]},{"name":"Barium Springs","zips":["28010"]},{"name":"Barnardsville","zips":["28709"]},{"name":"Barnesville","zips":["28319"]},{"name":"Bat Cave","zips":["28710"]},{"name":"Bath","zips":["27808"]},{"name":"Battleboro","zips":["27809"]},{"name":"Bayboro","zips":["28515"]},{"name":"Bear Creek","zips":["27207"]},{"name":"Beaufort","zips":["28516"]},{"name":"Belews Creek","zips":["27009"]},{"name":"Belhaven","zips":["27810"]},{"name":"Bellarthur","zips":["27811"]},{"name":"Belmont","zips":["28012"]},{"name":"Belvidere","zips":["27919"]},{"name":"Bennett","zips":["27208"]},{"name":"Benson","zips":["27504"]},{"name":"Bessemer City","zips":["28016"]},{"name":"Bethania","zips":["27010"]},{"name":"Bethel","zips":["27812"]},{"name":"Beulaville","zips":["28518"]},{"name":"Biscoe","zips":["27209"]},{"name":"Black Creek","zips":["27813"]},{"name":"Black Mountain","zips":["28711"]},{"name":"Bladenboro","zips":["28320"]},{"name":"Blanch","zips":["27212"]},{"name":"Blounts Creek","zips":["27814"]},{"name":"Blowing Rock","zips":["28605"]},{"name":"Boiling Springs","zips":["28017"]},{"name":"Bolivia","zips":["28422"]},{"name":"Bolton","zips":["28423"]},{"name":"Bonlee","zips":["27213"]},{"name":"Boomer","zips":["28606"]},{"name":"Boone","zips":["28607","28608"]},{"name":"Boonville","zips":["27011"]},{"name":"Bostic","zips":["28018"]},{"name":"Brasstown","zips":["28902"]},{"name":"Brevard","zips":["28712"]},{"name":"Bridgeton","zips":["28519"]},{"name":"Broadway","zips":["27505"]},{"name":"Browns Summit","zips":["27214"]},{"name":"Brunswick","zips":["28424"]},{"name":"Bryson City","zips":["28713"]},{"name":"Buies Creek","zips":["27506"]},{"name":"Bullock","zips":["27507"]},{"name":"Bunn","zips":["27508"]},{"name":"Bunnlevel","zips":["28323"]},{"name":"Burgaw","zips":["28425"]},{"name":"Burlington","zips":["27215","27216","27217","27220"]},{"name":"Burlington House","zips":["27321"]},{"name":"Burnsville","zips":["28714"]},{"name":"Butner","zips":["27509"]},{"name":"Buxton","zips":["27920"]},{"name":"Bynum","zips":["27228"]},{"name":"Calabash","zips":["28467"]},{"name":"Calypso","zips":["28325"]},{"name":"Camden","zips":["27921"]},{"name":"Cameron","zips":["28326"]},{"name":"Camp Lejeune","zips":["28542","28547"]},{"name":"Candler","zips":["28715"]},{"name":"Candor","zips":["27229"]},{"name":"Canton","zips":["28716"]},{"name":"Caroleen","zips":["28019"]},{"name":"Carolina Beach","zips":["28428"]},{"name":"Carrboro","zips":["27510"]},{"name":"Carthage","zips":["28327"]},{"name":"Cary","zips":["27511","27512","27513","27518","27519"]},{"name":"Casar","zips":["28020"]},{"name":"Cashiers","zips":["28717"]},{"name":"Castalia","zips":["27816"]},{"name":"Castle Hayne","zips":["28429"]},{"name":"Catawba","zips":["28609"]},{"name":"Cedar Falls","zips":["27230"]},{"name":"Cedar Grove","zips":["27231"]},{"name":"Cedar Island","zips":["28520"]},{"name":"Cedar Mountain","zips":["28718"]},{"name":"Cerro Gordo","zips":["28430"]},{"name":"Chadbourn","zips":["28431"]},{"name":"Chapel Hill","zips":["27514","27515","27516","27517","27599"]},{"name":"Charlotte","zips":["28201","28202","28203","28204","28205","28206","28207","28208","28209","28210","28211","28212","28213","28214","28215","28216","28217","28218","28219","28220","28221","28222","28223","28224","28226","28227","28228","28229","28230","28231","28232","28233","28234","28235","28236","28237","28241","28242","28243","28244","28246","28247","28250","28253","28254","28255","28256","28258","28260","28262","28263","28265","28266","28269","28270","28271","28272","28273","28274","28275","28277","28278","28280","28281","28282","28284","28285","28287","28288","28289","28290","28296","28297","28299"]},{"name":"Cherokee","zips":["28719"]},{"name":"Cherry Point","zips":["28533"]},{"name":"Cherryville","zips":["28021"]},{"name":"Chimney Rock","zips":["28720"]},{"name":"China Grove","zips":["28023"]},{"name":"Chinquapin","zips":["28521"]},{"name":"Chocowinity","zips":["27817"]},{"name":"Claremont","zips":["28610"]},{"name":"Clarendon","zips":["28432"]},{"name":"Clarkton","zips":["28433"]},{"name":"Clayton","zips":["27520","27527","27528"]},{"name":"Clemmons","zips":["27012"]},{"name":"Cleveland","zips":["27013"]},{"name":"Cliffside","zips":["28024"]},{"name":"Climax","zips":["27233"]},{"name":"Clinton","zips":["28328","28329"]},{"name":"Clyde","zips":["28721"]},{"name":"Coats","zips":["27521"]},{"name":"Cofield","zips":["27922"]},{"name":"Coinjock","zips":["27923"]},{"name":"Colerain","zips":["27924"]},{"name":"Colfax","zips":["27235"]},{"name":"Collettsville","zips":["28611"]},{"name":"Columbia","zips":["27925"]},{"name":"Columbus","zips":["28722"]},{"name":"Comfort","zips":["28522"]},{"name":"Como","zips":["27818"]},{"name":"Concord","zips":["28025","28026","28027"]},{"name":"Conetoe","zips":["27819"]},{"name":"Connellys Springs","zips":["28612"]},{"name":"Conover","zips":["28613"]},{"name":"Conway","zips":["27820"]},{"name":"Cooleemee","zips":["27014"]},{"name":"Corapeake","zips":["27926"]},{"name":"Cordova","zips":["28330"]},{"name":"Cornelius","zips":["28031"]},{"name":"Corolla","zips":["27927"]},{"name":"Council","zips":["28434"]},{"name":"Cove City","zips":["28523"]},{"name":"Cramerton","zips":["28032"]},{"name":"Creedmoor","zips":["27522","27564"]},{"name":"Creston","zips":["28615"]},{"name":"Creswell","zips":["27928"]},{"name":"Crossnore","zips":["28616"]},{"name":"Crouse","zips":["28033"]},{"name":"Crumpler","zips":["28617"]},{"name":"Culberson","zips":["28903"]},{"name":"Cullowhee","zips":["28723"]},{"name":"Cumberland","zips":["28331"]},{"name":"Cumnock","zips":["27237"]},{"name":"Currie","zips":["28435"]},{"name":"Currituck","zips":["27929"]},{"name":"Dallas","zips":["28034"]},{"name":"Dana","zips":["28724"]},{"name":"Danbury","zips":["27016"]},{"name":"Davidson","zips":["28035","28036"]},{"name":"Davis","zips":["28524"]},{"name":"Deep Gap","zips":["28618"]},{"name":"Deep Run","zips":["28525"]},{"name":"Delco","zips":["28436"]},{"name":"Denton","zips":["27239"]},{"name":"Denver","zips":["28037"]},{"name":"Dillsboro","zips":["28725"]},{"name":"Dobson","zips":["27017"]},{"name":"Dover","zips":["28526"]},{"name":"Drexel","zips":["28619"]},{"name":"Dublin","zips":["28332"]},{"name":"Dudley","zips":["28333"]},{"name":"Dunn","zips":["28334","28335"]},{"name":"Durants Neck","zips":["27930"]},{"name":"Durham","zips":["27701","27702","27703","27704","27705","27706","27707","27708","27709","27710","27711","27712","27713","27715","27717","27722"]},{"name":"Eagle Springs","zips":["27242"]},{"name":"Earl","zips":["28038"]},{"name":"East Bend","zips":["27018"]},{"name":"East Flat Rock","zips":["28726"]},{"name":"East Spencer","zips":["28039"]},{"name":"Eden","zips":["27288","27289"]},{"name":"Edenton","zips":["27932"]},{"name":"Edneyville","zips":["28727"]},{"name":"Edward","zips":["27821"]},{"name":"Efland","zips":["27243"]},{"name":"Elizabeth City","zips":["27906","27907","27909"]},{"name":"Elizabethtown","zips":["28337"]},{"name":"Elk Park","zips":["28622"]},{"name":"Elkin","zips":["28621"]},{"name":"Ellenboro","zips":["28040"]},{"name":"Ellerbe","zips":["28338"]},{"name":"Elm City","zips":["27822"]},{"name":"Elon","zips":["27244"]},{"name":"Emerald Isle","zips":["28594"]},{"name":"Enfield","zips":["27823"]},{"name":"Engelhard","zips":["27824"]},{"name":"Enka","zips":["28728"]},{"name":"Ennice","zips":["28623"]},{"name":"Ernul","zips":["28527"]},{"name":"Erwin","zips":["28339"]},{"name":"Ether","zips":["27247"]},{"name":"Etowah","zips":["28729"]},{"name":"Eure","zips":["27935"]},{"name":"Everetts","zips":["27825"]},{"name":"Evergreen","zips":["28438"]},{"name":"Fair Bluff","zips":["28439"]},{"name":"Fairfield","zips":["27826"]},{"name":"Fairmont","zips":["28340"]},{"name":"Fairview","zips":["28730"]},{"name":"Faison","zips":["28341"]},{"name":"Faith","zips":["28041"]},{"name":"Falcon","zips":["28342"]},{"name":"Falkland","zips":["27827"]},{"name":"Fallston","zips":["28042"]},{"name":"Farmville","zips":["27828"]},{"name":"Fayetteville","zips":["28301","28302","28303","28304","28305","28306","28309","28311","28312","28314"]},{"name":"Ferguson","zips":["28624"]},{"name":"Flat Rock","zips":["28731"]},{"name":"Fleetwood","zips":["28626"]},{"name":"Fletcher","zips":["28732"]},{"name":"Fontana Dam","zips":["28733"]},{"name":"Forest City","zips":["28043"]},{"name":"Fort Bragg","zips":["28307","28310"]},{"name":"Fountain","zips":["27829"]},{"name":"Four Oaks","zips":["27524"]},{"name":"Franklin","zips":["28734","28744"]},{"name":"Franklinton","zips":["27525"]},{"name":"Franklinville","zips":["27248"]},{"name":"Fremont","zips":["27830"]},{"name":"Frisco","zips":["27936"]},{"name":"Fuquay Varina","zips":["27526"]},{"name":"Garland","zips":["28441"]},{"name":"Garner","zips":["27529"]},{"name":"Garysburg","zips":["27831"]},{"name":"Gaston","zips":["27832"]},{"name":"Gastonia","zips":["28052","28053","28054","28055","28056"]},{"name":"Gates","zips":["27937"]},{"name":"Gatesville","zips":["27938"]},{"name":"Germanton","zips":["27019"]},{"name":"Gerton","zips":["28735"]},{"name":"Gibson","zips":["28343"]},{"name":"Gibsonville","zips":["27249"]},{"name":"Glade Valley","zips":["28627"]},{"name":"Glen Alpine","zips":["28628"]},{"name":"Glendale Springs","zips":["28629"]},{"name":"Glenville","zips":["28736"]},{"name":"Glenwood","zips":["28737"]},{"name":"Gloucester","zips":["28528"]},{"name":"Godwin","zips":["28344"]},{"name":"Gold Hill","zips":["28071"]},{"name":"Goldsboro","zips":["27530","27531","27532","27533","27534"]},{"name":"Goldston","zips":["27252"]},{"name":"Graham","zips":["27253"]},{"name":"Grandy","zips":["27939"]},{"name":"Granite Falls","zips":["28630"]},{"name":"Granite Quarry","zips":["28072"]},{"name":"Grantsboro","zips":["28529"]},{"name":"Grassy Creek","zips":["28631"]},{"name":"Green Mountain","zips":["28740"]},{"name":"Greensboro","zips":["27395","27401","27402","27403","27404","27405","27406","27407","27408","27409","27410","27411","27412","27413","27415","27416","27417","27419","27420","27425","27427","27429","27435","27438","27455","27495","27497","27498","27499"]},{"name":"Greenville","zips":["27833","27834","27835","27836","27858"]},{"name":"Grifton","zips":["28530"]},{"name":"Grimesland","zips":["27837"]},{"name":"Grover","zips":["28073"]},{"name":"Gulf","zips":["27256"]},{"name":"Halifax","zips":["27839"]},{"name":"Hallsboro","zips":["28442"]},{"name":"Hamilton","zips":["27840"]},{"name":"Hamlet","zips":["28345"]},{"name":"Hampstead","zips":["28443"]},{"name":"Hamptonville","zips":["27020"]},{"name":"Harbinger","zips":["27941"]},{"name":"Harkers Island","zips":["28531"]},{"name":"Harmony","zips":["28634"]},{"name":"Harrells","zips":["28444"]},{"name":"Harrellsville","zips":["27942"]},{"name":"Harris","zips":["28074"]},{"name":"Harrisburg","zips":["28075"]},{"name":"Hassell","zips":["27841"]},{"name":"Hatteras","zips":["27943"]},{"name":"Havelock","zips":["28532"]},{"name":"Haw River","zips":["27258"]},{"name":"Hayesville","zips":["28904"]},{"name":"Hays","zips":["28635"]},{"name":"Hazelwood","zips":["28738"]},{"name":"Henderson","zips":["27536","27537"]},{"name":"Hendersonville","zips":["28739","28791","28792","28793"]},{"name":"Henrico","zips":["27842"]},{"name":"Henrietta","zips":["28076"]},{"name":"Hertford","zips":["27944"]},{"name":"Hickory","zips":["28601","28602","28603"]},{"name":"Hiddenite","zips":["28636"]},{"name":"High Point","zips":["27260","27261","27262","27263","27264","27265","27268"]},{"name":"High Shoals","zips":["28077"]},{"name":"Highfalls","zips":["27259"]},{"name":"Highlands","zips":["28741"]},{"name":"Hildebran","zips":["28637"]},{"name":"Hillsborough","zips":["27278"]},{"name":"Hobbsville","zips":["27946"]},{"name":"Hobgood","zips":["27843"]},{"name":"Hobucken","zips":["28537"]},{"name":"Hoffman","zips":["28347"]},{"name":"Hollister","zips":["27844"]},{"name":"Holly Ridge","zips":["28445"]},{"name":"Holly Springs","zips":["27540"]},{"name":"Hookerton","zips":["28538"]},{"name":"Hope Mills","zips":["28348"]},{"name":"Horse Shoe","zips":["28742"]},{"name":"Hot Springs","zips":["28743"]},{"name":"Hubert","zips":["28539"]},{"name":"Hudson","zips":["28638"]},{"name":"Huntersville","zips":["28070","28078"]},{"name":"Hurdle Mills","zips":["27541"]},{"name":"Icard","zips":["28666"]},{"name":"Indian Trail","zips":["28079"]},{"name":"Iron Station","zips":["28080"]},{"name":"Ivanhoe","zips":["28447"]},{"name":"Jackson","zips":["27845"]},{"name":"Jackson Springs","zips":["27281"]},{"name":"Jacksonville","zips":["28540","28541","28546"]},{"name":"Jamestown","zips":["27282"]},{"name":"Jamesville","zips":["27846"]},{"name":"Jarvisburg","zips":["27947"]},{"name":"Jefferson","zips":["28640"]},{"name":"Jonas Ridge","zips":["28641"]},{"name":"Jonesville","zips":["28642"]},{"name":"Julian","zips":["27283"]},{"name":"Kannapolis","zips":["28081","28082","28083"]},{"name":"Kelford","zips":["27847"]},{"name":"Kelly","zips":["28448"]},{"name":"Kenansville","zips":["28349"]},{"name":"Kenly","zips":["27542"]},{"name":"Kernersville","zips":["27284","27285"]},{"name":"Kill Devil Hills","zips":["27948"]},{"name":"King","zips":["27021"]},{"name":"Kings Mountain","zips":["28086"]},{"name":"Kinston","zips":["28501","28502","28503","28504"]},{"name":"Kipling","zips":["27543"]},{"name":"Kittrell","zips":["27544"]},{"name":"Kitty Hawk","zips":["27949"]},{"name":"Knightdale","zips":["27545"]},{"name":"Knotts Island","zips":["27950"]},{"name":"Kure Beach","zips":["28449"]},{"name":"La Grange","zips":["28551"]},{"name":"Lake Junaluska","zips":["28745"]},{"name":"Lake Lure","zips":["28746"]},{"name":"Lake Toxaway","zips":["28747"]},{"name":"Lake Waccamaw","zips":["28450"]},{"name":"Lakeview","zips":["28350"]},{"name":"Landis","zips":["28088"]},{"name":"Lansing","zips":["28643"]},{"name":"Lattimore","zips":["28089"]},{"name":"Laurel Hill","zips":["28351"]},{"name":"Laurel Springs","zips":["28644"]},{"name":"Laurinburg","zips":["28352","28353"]},{"name":"Lawndale","zips":["28090"]},{"name":"Lawsonville","zips":["27022"]},{"name":"Leasburg","zips":["27291"]},{"name":"Leicester","zips":["28748"]},{"name":"Leland","zips":["28451"]},{"name":"Lemon Springs","zips":["28355"]},{"name":"Lenoir","zips":["28633","28645"]},{"name":"Lewiston Woodville","zips":["27849"]},{"name":"Lewisville","zips":["27023"]},{"name":"Lexington","zips":["27292","27293","27294","27295"]},{"name":"Liberty","zips":["27298"]},{"name":"Lilesville","zips":["28091"]},{"name":"Lillington","zips":["27546"]},{"name":"Lincolnton","zips":["28092","28093"]},{"name":"Linden","zips":["28356"]},{"name":"Linville","zips":["28646"]},{"name":"Linville Falls","zips":["28647"]},{"name":"Linwood","zips":["27299"]},{"name":"Little Switzerland","zips":["28749"]},{"name":"Littleton","zips":["27850"]},{"name":"Locust","zips":["28097"]},{"name":"Longwood","zips":["28452"]},{"name":"Louisburg","zips":["27549"]},{"name":"Lowell","zips":["28098"]},{"name":"Lowgap","zips":["27024"]},{"name":"Lowland","zips":["28552"]},{"name":"Lucama","zips":["27851"]},{"name":"Lumber Bridge","zips":["28357"]},{"name":"Lumberton","zips":["28358","28359","28360"]},{"name":"Lynn","zips":["28750"]},{"name":"Macclesfield","zips":["27852"]},{"name":"Macon","zips":["27551"]},{"name":"Madison","zips":["27025"]},{"name":"Maggie Valley","zips":["28751"]},{"name":"Magnolia","zips":["28453"]},{"name":"Maiden","zips":["28650"]},{"name":"Mamers","zips":["27552"]},{"name":"Manns Harbor","zips":["27953"]},{"name":"Manson","zips":["27553"]},{"name":"Manteo","zips":["27954"]},{"name":"Maple","zips":["27956"]},{"name":"Maple Hill","zips":["28454"]},{"name":"Marble","zips":["28905"]},{"name":"Margarettsville","zips":["27853"]},{"name":"Marietta","zips":["28362"]},{"name":"Marion","zips":["28752"]},{"name":"Mars Hill","zips":["28754"]},{"name":"Marshall","zips":["28753"]},{"name":"Marshallberg","zips":["28553"]},{"name":"Marshville","zips":["28103"]},{"name":"Marston","zips":["28363"]},{"name":"Matthews","zips":["28104","28105","28106"]},{"name":"Maury","zips":["28554"]},{"name":"Maxton","zips":["28364"]},{"name":"Mayodan","zips":["27027"]},{"name":"Maysville","zips":["28555"]},{"name":"Mc Adenville","zips":["28101"]},{"name":"Mc Farlan","zips":["28102"]},{"name":"Mc Grady","zips":["28649"]},{"name":"Mc Leansville","zips":["27301"]},{"name":"Mccutcheon Field","zips":["28545"]},{"name":"Mebane","zips":["27302"]},{"name":"Merritt","zips":["28556"]},{"name":"Merry Hill","zips":["27957"]},{"name":"Micaville","zips":["28755"]},{"name":"Micro","zips":["27555"]},{"name":"Middleburg","zips":["27556"]},{"name":"Middlesex","zips":["27557"]},{"name":"Midland","zips":["28107"]},{"name":"Midway Park","zips":["28544"]},{"name":"Mill Spring","zips":["28756"]},{"name":"Millers Creek","zips":["28651"]},{"name":"Mills River","zips":["28759"]},{"name":"Milton","zips":["27305"]},{"name":"Milwaukee","zips":["27854"]},{"name":"Mineral Springs","zips":["28108"]},{"name":"Minneapolis","zips":["28652"]},{"name":"Misenheimer","zips":["28109"]},{"name":"Mocksville","zips":["27028"]},{"name":"Moncure","zips":["27559"]},{"name":"Monroe","zips":["28110","28111","28112"]},{"name":"Montezuma","zips":["28653"]},{"name":"Montreat","zips":["28757"]},{"name":"Mooresboro","zips":["28114"]},{"name":"Mooresville","zips":["28115","28117"]},{"name":"Moravian Falls","zips":["28654"]},{"name":"Morehead City","zips":["28557"]},{"name":"Morganton","zips":["28655","28680"]},{"name":"Morrisville","zips":["27560"]},{"name":"Morven","zips":["28119"]},{"name":"Mount Airy","zips":["27030"]},{"name":"Mount Gilead","zips":["27306"]},{"name":"Mount Holly","zips":["28120"]},{"name":"Mount Mourne","zips":["28123"]},{"name":"Mount Olive","zips":["28365"]},{"name":"Mount Pleasant","zips":["28124"]},{"name":"Mount Ulla","zips":["28125"]},{"name":"Mountain Home","zips":["28758"]},{"name":"Moyock","zips":["27958"]},{"name":"Murfreesboro","zips":["27855"]},{"name":"Murphy","zips":["28906"]},{"name":"Nags Head","zips":["27959"]},{"name":"Nakina","zips":["28455"]},{"name":"Naples","zips":["28760"]},{"name":"Nashville","zips":["27856"]},{"name":"Nebo","zips":["28761"]},{"name":"New Bern","zips":["28560","28561","28562","28563","28564"]},{"name":"New Hill","zips":["27562"]},{"name":"New London","zips":["28127"]},{"name":"Newell","zips":["28126"]},{"name":"Newland","zips":["28657"]},{"name":"Newport","zips":["28570"]},{"name":"Newton","zips":["28658"]},{"name":"Newton Grove","zips":["28366"]},{"name":"Norlina","zips":["27563"]},{"name":"Norman","zips":["28367"]},{"name":"North Wilkesboro","zips":["28656","28659","28674"]},{"name":"Norwood","zips":["28128"]},{"name":"Oak City","zips":["27857"]},{"name":"Oak Island","zips":["28465"]},{"name":"Oak Ridge","zips":["27310"]},{"name":"Oakboro","zips":["28129"]},{"name":"Ocean Isle Beach","zips":["28469"]},{"name":"Ocracoke","zips":["27960"]},{"name":"Old Fort","zips":["28762"]},{"name":"Olin","zips":["28660"]},{"name":"Olivia","zips":["28368"]},{"name":"Oriental","zips":["28571"]},{"name":"Orrum","zips":["28369"]},{"name":"Otto","zips":["28763"]},{"name":"Oxford","zips":["27565"]},{"name":"Pantego","zips":["27860"]},{"name":"Parkton","zips":["28371"]},{"name":"Parmele","zips":["27861"]},{"name":"Patterson","zips":["28661"]},{"name":"Paw Creek","zips":["28130"]},{"name":"Peachland","zips":["28133"]},{"name":"Pelham","zips":["27311"]},{"name":"Pembroke","zips":["28372"]},{"name":"Pendleton","zips":["27862"]},{"name":"Penland","zips":["28765"]},{"name":"Penrose","zips":["28766"]},{"name":"Pfafftown","zips":["27040"]},{"name":"Piedmont Aviation","zips":["27156"]},{"name":"Pikeville","zips":["27863"]},{"name":"Pilot Mountain","zips":["27041"]},{"name":"Pine Hall","zips":["27042"]},{"name":"Pine Level","zips":["27568"]},{"name":"Pinebluff","zips":["28373"]},{"name":"Pinehurst","zips":["28370","28374"]},{"name":"Pineola","zips":["28662"]},{"name":"Pinetops","zips":["27864"]},{"name":"Pinetown","zips":["27865"]},{"name":"Pineville","zips":["28134"]},{"name":"Piney Creek","zips":["28663"]},{"name":"Pink Hill","zips":["28572"]},{"name":"Pinnacle","zips":["27043"]},{"name":"Pisgah Forest","zips":["28768"]},{"name":"Pittsboro","zips":["27312"]},{"name":"Pleasant Garden","zips":["27313"]},{"name":"Pleasant Hill","zips":["27866"]},{"name":"Plumtree","zips":["28664"]},{"name":"Plymouth","zips":["27962"]},{"name":"Point Harbor","zips":["27964"]},{"name":"Polkton","zips":["28135"]},{"name":"Polkville","zips":["28136"]},{"name":"Pollocksville","zips":["28573"]},{"name":"Pope Army Airfield","zips":["28308"]},{"name":"Poplar Branch","zips":["27965"]},{"name":"Potecasi","zips":["27867"]},{"name":"Powells Point","zips":["27966"]},{"name":"Powellsville","zips":["27967"]},{"name":"Princeton","zips":["27569"]},{"name":"Proctorville","zips":["28375"]},{"name":"Prospect Hill","zips":["27314"]},{"name":"Providence","zips":["27315"]},{"name":"Purlear","zips":["28665"]},{"name":"Raeford","zips":["28376"]},{"name":"Raleigh","zips":["27601","27602","27603","27604","27605","27606","27607","27608","27609","27610","27611","27612","27613","27614","27615","27616","27617","27619","27620","27621","27622","27623","27624","27625","27626","27627","27628","27629","27634","27635","27636","27640","27650","27656","27658","27661","27668","27675","27676","27690","27695","27697","27698","27699"]},{"name":"Ramseur","zips":["27316"]},{"name":"Randleman","zips":["27317"]},{"name":"Red Oak","zips":["27868"]},{"name":"Red Springs","zips":["28377"]},{"name":"Reidsville","zips":["27320","27322","27323"]},{"name":"Rex","zips":["28378"]},{"name":"Rhodhiss","zips":["28667"]},{"name":"Rich Square","zips":["27869"]},{"name":"Richfield","zips":["28137"]},{"name":"Richlands","zips":["28574"]},{"name":"Ridgecrest","zips":["28770"]},{"name":"Ridgeway","zips":["27570"]},{"name":"Riegelwood","zips":["28456"]},{"name":"Roanoke Rapids","zips":["27870"]},{"name":"Roaring Gap","zips":["28668"]},{"name":"Roaring River","zips":["28669"]},{"name":"Robbins","zips":["27325"]},{"name":"Robbinsville","zips":["28771"]},{"name":"Robersonville","zips":["27871"]},{"name":"Rockingham","zips":["28379","28380"]},{"name":"Rockwell","zips":["28138"]},{"name":"Rocky Mount","zips":["27801","27802","27803","27804","27815"]},{"name":"Rocky Point","zips":["28457"]},{"name":"Rodanthe","zips":["27968"]},{"name":"Roduco","zips":["27969"]},{"name":"Rolesville","zips":["27571"]},{"name":"Ronda","zips":["28670"]},{"name":"Roper","zips":["27970"]},{"name":"Rose Hill","zips":["28458"]},{"name":"Roseboro","zips":["28382"]},{"name":"Rosman","zips":["28772"]},{"name":"Rougemont","zips":["27572"]},{"name":"Rowland","zips":["28383"]},{"name":"Roxboro","zips":["27573","27574"]},{"name":"Roxobel","zips":["27872"]},{"name":"Ruffin","zips":["27326"]},{"name":"Rural Hall","zips":["27045","27094","27098","27099"]},{"name":"Rutherford College","zips":["28671"]},{"name":"Rutherfordton","zips":["28139"]},{"name":"Saint Pauls","zips":["28384"]},{"name":"Salemburg","zips":["28385"]},{"name":"Salisbury","zips":["28144","28145","28146","28147"]},{"name":"Salter Path","zips":["28575"]},{"name":"Saluda","zips":["28773"]},{"name":"Salvo","zips":["27972"]},{"name":"Sandy Ridge","zips":["27046"]},{"name":"Sanford","zips":["27330","27331","27332"]},{"name":"Sapphire","zips":["28774"]},{"name":"Saratoga","zips":["27873"]},{"name":"Saxapahaw","zips":["27340"]},{"name":"Scaly Mountain","zips":["28775"]},{"name":"Scotland Neck","zips":["27874"]},{"name":"Scotts","zips":["28699"]},{"name":"Scottville","zips":["28672"]},{"name":"Scranton","zips":["27875"]},{"name":"Seaboard","zips":["27876"]},{"name":"Seagrove","zips":["27341"]},{"name":"Sealevel","zips":["28577"]},{"name":"Sears Roebuck","zips":["27480"]},{"name":"Sedalia","zips":["27342"]},{"name":"Selma","zips":["27576"]},{"name":"Semora","zips":["27343"]},{"name":"Seven Springs","zips":["28578"]},{"name":"Severn","zips":["27877"]},{"name":"Shallotte","zips":["28459","28470"]},{"name":"Shannon","zips":["28386"]},{"name":"Sharpsburg","zips":["27878"]},{"name":"Shawboro","zips":["27973"]},{"name":"Shelby","zips":["28150","28151","28152"]},{"name":"Sherrills Ford","zips":["28673"]},{"name":"Shiloh","zips":["27974"]},{"name":"Siler City","zips":["27344"]},{"name":"Siloam","zips":["27047"]},{"name":"Simpson","zips":["27879"]},{"name":"Sims","zips":["27880"]},{"name":"Skyland","zips":["28776"]},{"name":"Smithfield","zips":["27577"]},{"name":"Smyrna","zips":["28579"]},{"name":"Sneads Ferry","zips":["28460"]},{"name":"Snow Camp","zips":["27349"]},{"name":"Snow Hill","zips":["28580"]},{"name":"Sophia","zips":["27350"]},{"name":"South Mills","zips":["27976"]},{"name":"Southern Pines","zips":["28387","28388"]},{"name":"Southmont","zips":["27351"]},{"name":"Southport","zips":["28461"]},{"name":"Sparta","zips":["28675"]},{"name":"Speed","zips":["27881"]},{"name":"Spencer","zips":["28159"]},{"name":"Spindale","zips":["28160"]},{"name":"Spring Hope","zips":["27882"]},{"name":"Spring Lake","zips":["28390"]},{"name":"Spruce Pine","zips":["28777"]},{"name":"Stacy","zips":["28581"]},{"name":"Staley","zips":["27355"]},{"name":"Stanfield","zips":["28163"]},{"name":"Stanley","zips":["28164"]},{"name":"Stantonsburg","zips":["27883"]},{"name":"Star","zips":["27356"]},{"name":"State Road","zips":["28676"]},{"name":"Statesville","zips":["28625","28677","28687"]},{"name":"Stedman","zips":["28391"]},{"name":"Stella","zips":["28582"]},{"name":"Stem","zips":["27581"]},{"name":"Stokes","zips":["27884"]},{"name":"Stokesdale","zips":["27357"]},{"name":"Stoneville","zips":["27048"]},{"name":"Stonewall","zips":["28583"]},{"name":"Stony Point","zips":["28678"]},{"name":"Stovall","zips":["27582"]},{"name":"Stumpy Point","zips":["27978"]},{"name":"Sugar Grove","zips":["28679"]},{"name":"Summerfield","zips":["27358"]},{"name":"Sunbury","zips":["27979"]},{"name":"Sunset Beach","zips":["28468"]},{"name":"Supply","zips":["28462"]},{"name":"Swannanoa","zips":["28778"]},{"name":"Swanquarter","zips":["27885"]},{"name":"Swansboro","zips":["28584"]},{"name":"Swepsonville","zips":["27359"]},{"name":"Sylva","zips":["28779"]},{"name":"Tabor City","zips":["28463"]},{"name":"Tar Heel","zips":["28392"]},{"name":"Tarawa Terrace","zips":["28543"]},{"name":"Tarboro","zips":["27886"]},{"name":"Taylorsville","zips":["28681"]},{"name":"Teachey","zips":["28464"]},{"name":"Terrell","zips":["28682"]},{"name":"Thomasville","zips":["27360","27361"]},{"name":"Thurmond","zips":["28683"]},{"name":"Tillery","zips":["27887"]},{"name":"Timberlake","zips":["27583"]},{"name":"Toast","zips":["27049"]},{"name":"Tobaccoville","zips":["27050"]},{"name":"Todd","zips":["28684"]},{"name":"Topton","zips":["28781"]},{"name":"Townsville","zips":["27584"]},{"name":"Traphill","zips":["28685"]},{"name":"Trenton","zips":["28585"]},{"name":"Trinity","zips":["27370"]},{"name":"Troutman","zips":["28166"]},{"name":"Troy","zips":["27371"]},{"name":"Tryon","zips":["28782"]},{"name":"Tuckasegee","zips":["28783"]},{"name":"Turkey","zips":["28393"]},{"name":"Turnersburg","zips":["28688"]},{"name":"Tuxedo","zips":["28784"]},{"name":"Tyner","zips":["27980"]},{"name":"Union Grove","zips":["28689"]},{"name":"Union Mills","zips":["28167"]},{"name":"Valdese","zips":["28690"]},{"name":"Vale","zips":["28168"]},{"name":"Valle Crucis","zips":["28691"]},{"name":"Vanceboro","zips":["28586"]},{"name":"Vandemere","zips":["28587"]},{"name":"Vass","zips":["28394"]},{"name":"Vaughan","zips":["27586"]},{"name":"Vilas","zips":["28692"]},{"name":"Wachovia Master Chrg","zips":["27151"]},{"name":"Waco","zips":["28169"]},{"name":"Wade","zips":["28395"]},{"name":"Wadesboro","zips":["28170"]},{"name":"Wagram","zips":["28396"]},{"name":"Wake Forest","zips":["27587","27588"]},{"name":"Walkertown","zips":["27051"]},{"name":"Wallace","zips":["28466"]},{"name":"Wallburg","zips":["27373"]},{"name":"Walnut Cove","zips":["27052"]},{"name":"Walstonburg","zips":["27888"]},{"name":"Wanchese","zips":["27981"]},{"name":"Warne","zips":["28909"]},{"name":"Warrensville","zips":["28693"]},{"name":"Warrenton","zips":["27589"]},{"name":"Warsaw","zips":["28398"]},{"name":"Washington","zips":["27889"]},{"name":"Waves","zips":["27982"]},{"name":"Waxhaw","zips":["28173"]},{"name":"Waynesville","zips":["28785","28786"]},{"name":"Weaverville","zips":["28787"]},{"name":"Webster","zips":["28788"]},{"name":"Welcome","zips":["27374"]},{"name":"Weldon","zips":["27890"]},{"name":"Wendell","zips":["27591"]},{"name":"Wentworth","zips":["27375"]},{"name":"West End","zips":["27376"]},{"name":"West Jefferson","zips":["28694"]},{"name":"Westfield","zips":["27053"]},{"name":"Whitakers","zips":["27891"]},{"name":"White Oak","zips":["28399"]},{"name":"White Plains","zips":["27031"]},{"name":"Whiteville","zips":["28472"]},{"name":"Whitsett","zips":["27377"]},{"name":"Whittier","zips":["28789"]},{"name":"Wilkesboro","zips":["28697"]},{"name":"Willard","zips":["28478"]},{"name":"Williamston","zips":["27892"]},{"name":"Williston","zips":["28589"]},{"name":"Willow Spring","zips":["27592"]},{"name":"Wilmington","zips":["28401","28402","28403","28404","28405","28406","28407","28408","28409","28410","28411","28412"]},{"name":"Wilson","zips":["27893","27894","27895","27896"]},{"name":"Wilsons Mills","zips":["27593"]},{"name":"Windsor","zips":["27983"]},{"name":"Winfall","zips":["27985"]},{"name":"Wingate","zips":["28174"]},{"name":"Winnabow","zips":["28479"]},{"name":"Winston Salem","zips":["27101","27102","27103","27104","27105","27106","27107","27108","27109","27110","27111","27113","27114","27115","27116","27117","27120","27127","27130","27150","27152","27155","27157","27198","27199"]},{"name":"Winterville","zips":["28590"]},{"name":"Winton","zips":["27986"]},{"name":"Wise","zips":["27594"]},{"name":"Woodland","zips":["27897"]},{"name":"Woodleaf","zips":["27054"]},{"name":"Wrightsville Beach","zips":["28480"]},{"name":"Yadkinville","zips":["27055"]},{"name":"Yanceyville","zips":["27379"]},{"name":"Youngsville","zips":["27596"]},{"name":"Zebulon","zips":["27597"]},{"name":"Zionville","zips":["28698"]},{"name":"Zirconia","zips":["28790"]}]}