{"cities":[{"name":"Adams","zips":["37010"]},{"name":"Adamsville","zips":["38310"]},{"name":"Afton","zips":["37616"]},{"name":"Alamo","zips":["38001"]},{"name":"Alcoa","zips":["37701"]},{"name":"Alexandria","zips":["37012"]},{"name":"Allardt","zips":["38504"]},{"name":"Allons","zips":["38541"]},{"name":"Allred","zips":["38542"]},{"name":"Alpine","zips":["38543"]},{"name":"Altamont","zips":["37301"]},{"name":"Amsouth Bank","zips":["37237"]},{"name":"Andersonville","zips":["37705"]},{"name":"Antioch","zips":["37011","37013"]},{"name":"Apison","zips":["37302"]},{"name":"Ardmore","zips":["38449"]},{"name":"Arlington","zips":["38002"]},{"name":"Arnold Afb","zips":["37389"]},{"name":"Arrington","zips":["37014"]},{"name":"Arthur","zips":["37707"]},{"name":"Ashland City","zips":["37015"]},{"name":"Athens","zips":["37303","37371"]},{"name":"Atoka","zips":["38004"]},{"name":"Atwood","zips":["38220"]},{"name":"Auburntown","zips":["37016"]},{"name":"Bakewell","zips":["37304"]},{"name":"Bath Springs","zips":["38311"]},{"name":"Baxter","zips":["38544"]},{"name":"Bean Station","zips":["37708"]},{"name":"Beech Bluff","zips":["38313"]},{"name":"Beechgrove","zips":["37018"]},{"name":"Beersheba Springs","zips":["37305"]},{"name":"Belfast","zips":["37019"]},{"name":"Bell Buckle","zips":["37020"]},{"name":"Bells","zips":["38006"]},{"name":"Belvidere","zips":["37306"]},{"name":"Benton","zips":["37307"]},{"name":"Bethel Springs","zips":["38315"]},{"name":"Bethpage","zips":["37022"]},{"name":"Big Rock","zips":["37023"]},{"name":"Big Sandy","zips":["38221"]},{"name":"Birchwood","zips":["37308"]},{"name":"Blaine","zips":["37709"]},{"name":"Bloomington Springs","zips":["38545"]},{"name":"Blountville","zips":["37617"]},{"name":"Bluff City","zips":["37618"]},{"name":"Bogota","zips":["38007"]},{"name":"Bolivar","zips":["38008"]},{"name":"Bon Aqua","zips":["37025"]},{"name":"Braden","zips":["38010"]},{"name":"Bradford","zips":["38316"]},{"name":"Bradyville","zips":["37026"]},{"name":"Brentwood","zips":["37024","37027"]},{"name":"Briceville","zips":["37710"]},{"name":"Brighton","zips":["38011"]},{"name":"Bristol","zips":["37620","37621","37625"]},{"name":"Brownsville","zips":["38012"]},{"name":"Bruceton","zips":["38317"]},{"name":"Brunswick","zips":["38014"]},{"name":"Brush Creek","zips":["38547"]},{"name":"Buchanan","zips":["38222"]},{"name":"Buena Vista","zips":["38318"]},{"name":"Buffalo Valley","zips":["38548"]},{"name":"Bulls Gap","zips":["37711"]},{"name":"Bumpus Mills","zips":["37028"]},{"name":"Burlison","zips":["38015"]},{"name":"Burns","zips":["37029"]},{"name":"Butler","zips":["37640"]},{"name":"Bybee","zips":["37713"]},{"name":"Byrdstown","zips":["38549"]},{"name":"Calhoun","zips":["37309"]},{"name":"Camden","zips":["38320"]},{"name":"Campaign","zips":["38550"]},{"name":"Carthage","zips":["37030"]},{"name":"Caryville","zips":["37714"]},{"name":"Castalian Springs","zips":["37031"]},{"name":"Cedar Grove","zips":["38321"]},{"name":"Cedar Hill","zips":["37032"]},{"name":"Celina","zips":["38551"]},{"name":"Centerville","zips":["37033"]},{"name":"Chapel Hill","zips":["37034"]},{"name":"Chapmansboro","zips":["37035"]},{"name":"Charleston","zips":["37310"]},{"name":"Charlotte","zips":["37036"]},{"name":"Chattanooga","zips":["37401","37402","37403","37404","37405","37406","37407","37408","37409","37410","37411","37412","37414","37415","37416","37419","37421","37422","37424","37450"]},{"name":"Chestnut Mound","zips":["38552"]},{"name":"Chewalla","zips":["38393"]},{"name":"Christiana","zips":["37037"]},{"name":"Chuckey","zips":["37641"]},{"name":"Church Hill","zips":["37642"]},{"name":"Clairfield","zips":["37715"]},{"name":"Clarkrange","zips":["38553"]},{"name":"Clarksburg","zips":["38324"]},{"name":"Clarksville","zips":["37040","37041","37042","37043","37044"]},{"name":"Cleveland","zips":["37311","37312","37320","37323","37364"]},{"name":"Clifton","zips":["38425"]},{"name":"Clinton","zips":["37716","37717"]},{"name":"Coalfield","zips":["37719"]},{"name":"Coalmont","zips":["37313"]},{"name":"Coker Creek","zips":["37314"]},{"name":"College Grove","zips":["37046"]},{"name":"Collegedale","zips":["37315"]},{"name":"Collierville","zips":["38017","38027"]},{"name":"Collinwood","zips":["38450"]},{"name":"Columbia","zips":["38401","38402"]},{"name":"Como","zips":["38223"]},{"name":"Conasauga","zips":["37316"]},{"name":"Cookeville","zips":["38501","38502","38503","38505","38506"]},{"name":"Copperhill","zips":["37317"]},{"name":"Cordova","zips":["38016","38018","38088"]},{"name":"Cornersville","zips":["37047"]},{"name":"Corryton","zips":["37721"]},{"name":"Cosby","zips":["37722"]},{"name":"Cottage Grove","zips":["38224"]},{"name":"Cottontown","zips":["37048"]},{"name":"Counce","zips":["38326"]},{"name":"Covington","zips":["38019"]},{"name":"Cowan","zips":["37318"]},{"name":"Crab Orchard","zips":["37723"]},{"name":"Crawford","zips":["38554"]},{"name":"Crockett Mills","zips":["38021"]},{"name":"Cross Plains","zips":["37049"]},{"name":"Crossville","zips":["38555","38557","38558","38571","38572"]},{"name":"Crump","zips":["38327"]},{"name":"Culleoka","zips":["38451"]},{"name":"Cumberland City","zips":["37050"]},{"name":"Cumberland Furnace","zips":["37051"]},{"name":"Cumberland Gap","zips":["37724"]},{"name":"Cunningham","zips":["37052"]},{"name":"Cypress Inn","zips":["38452"]},{"name":"Dandridge","zips":["37725"]},{"name":"Darden","zips":["38328"]},{"name":"Dayton","zips":["37321"]},{"name":"Decatur","zips":["37322"]},{"name":"Decaturville","zips":["38329"]},{"name":"Decherd","zips":["37324"]},{"name":"Deer Lodge","zips":["37726"]},{"name":"Del Rio","zips":["37727"]},{"name":"Delano","zips":["37325"]},{"name":"Dellrose","zips":["38453"]},{"name":"Denmark","zips":["38391"]},{"name":"Dickson","zips":["37055","37056"]},{"name":"Dixon Springs","zips":["37057"]},{"name":"Dover","zips":["37058"]},{"name":"Dowelltown","zips":["37059"]},{"name":"Doyle","zips":["38559"]},{"name":"Dresden","zips":["38225"]},{"name":"Drummonds","zips":["38023"]},{"name":"Duck River","zips":["38454"]},{"name":"Ducktown","zips":["37326"]},{"name":"Duff","zips":["37729"]},{"name":"Dukedom","zips":["38226"]},{"name":"Dunlap","zips":["37327"]},{"name":"Dyer","zips":["38330"]},{"name":"Dyersburg","zips":["38024","38025"]},{"name":"Eads","zips":["38028"]},{"name":"Eagan","zips":["37730"]},{"name":"Eagleville","zips":["37060"]},{"name":"Eaton","zips":["38331"]},{"name":"Eidson","zips":["37731"]},{"name":"Elbridge","zips":["38227"]},{"name":"Elgin","zips":["37732"]},{"name":"Elizabethton","zips":["37643","37644"]},{"name":"Elkton","zips":["38455"]},{"name":"Ellendale","zips":["38029"]},{"name":"Elmwood","zips":["38560"]},{"name":"Elora","zips":["37328"]},{"name":"Englewood","zips":["37329"]},{"name":"Enville","zips":["38332"]},{"name":"Erin","zips":["37061"]},{"name":"Erwin","zips":["37650"]},{"name":"Estill Springs","zips":["37330"]},{"name":"Ethridge","zips":["38456"]},{"name":"Etowah","zips":["37331"]},{"name":"Eva","zips":["38333"]},{"name":"Evensville","zips":["37332"]},{"name":"Fairview","zips":["37062"]},{"name":"Fall Branch","zips":["37656"]},{"name":"Farner","zips":["37333"]},{"name":"Fayetteville","zips":["37334"]},{"name":"Finger","zips":["38334"]},{"name":"Finley","zips":["38030"]},{"name":"Five Points","zips":["38457"]},{"name":"Flag Pond","zips":["37657"]},{"name":"Flintville","zips":["37335"]},{"name":"Fosterville","zips":["37063"]},{"name":"Frankewing","zips":["38459"]},{"name":"Franklin","zips":["37064","37065","37067","37068","37069"]},{"name":"Friendship","zips":["38034"]},{"name":"Friendsville","zips":["37737"]},{"name":"Fruitvale","zips":["38336"]},{"name":"Gadsden","zips":["38337"]},{"name":"Gainesboro","zips":["38562"]},{"name":"Gallatin","zips":["37066"]},{"name":"Gallaway","zips":["38036"]},{"name":"Gates","zips":["38037"]},{"name":"Gatlinburg","zips":["37738"]},{"name":"Georgetown","zips":["37336"]},{"name":"Germantown","zips":["38138","38139","38183"]},{"name":"Gibson","zips":["38338"]},{"name":"Gladeville","zips":["37071"]},{"name":"Gleason","zips":["38229"]},{"name":"Goodlettsville","zips":["37070","37072"]},{"name":"Goodspring","zips":["38460"]},{"name":"Gordonsville","zips":["38563"]},{"name":"Grand Junction","zips":["38039"]},{"name":"Grandview","zips":["37337"]},{"name":"Granville","zips":["38564"]},{"name":"Graysville","zips":["37338"]},{"name":"Greenback","zips":["37742"]},{"name":"Greenbrier","zips":["37073"]},{"name":"Greeneville","zips":["37743","37744","37745"]},{"name":"Greenfield","zips":["38230"]},{"name":"Grimsley","zips":["38565"]},{"name":"Gruetli Laager","zips":["37339"]},{"name":"Guild","zips":["37340"]},{"name":"Guys","zips":["38339"]},{"name":"Halls","zips":["38040"]},{"name":"Hampshire","zips":["38461"]},{"name":"Hampton","zips":["37658"]},{"name":"Harriman","zips":["37748"]},{"name":"Harrison","zips":["37341"]},{"name":"Harrogate","zips":["37752"]},{"name":"Hartford","zips":["37753"]},{"name":"Hartsville","zips":["37074"]},{"name":"Heiskell","zips":["37754"]},{"name":"Helenwood","zips":["37755"]},{"name":"Henderson","zips":["38340"]},{"name":"Hendersonville","zips":["37075","37077"]},{"name":"Henning","zips":["38041"]},{"name":"Henry","zips":["38231"]},{"name":"Hermitage","zips":["37076"]},{"name":"Hickman","zips":["38567"]},{"name":"Hickory Valley","zips":["38042"]},{"name":"Hilham","zips":["38568"]},{"name":"Hillsboro","zips":["37342"]},{"name":"Hixson","zips":["37343"]},{"name":"Hohenwald","zips":["38462"]},{"name":"Holladay","zips":["38341"]},{"name":"Hollow Rock","zips":["38342"]},{"name":"Hornbeak","zips":["38232"]},{"name":"Hornsby","zips":["38044"]},{"name":"Humboldt","zips":["38343"]},{"name":"Huntingdon","zips":["38344"]},{"name":"Huntland","zips":["37345"]},{"name":"Huntsville","zips":["37756"]},{"name":"Huron","zips":["38345"]},{"name":"Hurricane Mills","zips":["37078"]},{"name":"Idlewild","zips":["38346"]},{"name":"Indian Mound","zips":["37079"]},{"name":"Iron City","zips":["38463"]},{"name":"Jacks Creek","zips":["38347"]},{"name":"Jacksboro","zips":["37757"]},{"name":"Jackson","zips":["38301","38302","38303","38305","38308","38314"]},{"name":"Jamestown","zips":["38556"]},{"name":"Jasper","zips":["37347"]},{"name":"Jefferson City","zips":["37760"]},{"name":"Jellico","zips":["37762"]},{"name":"Joelton","zips":["37080"]},{"name":"Johnson City","zips":["37601","37602","37604","37605","37614","37615"]},{"name":"Jonesborough","zips":["37659"]},{"name":"Kelso","zips":["37348"]},{"name":"Kenton","zips":["38233"]},{"name":"Kingsport","zips":["37660","37662","37663","37664","37665","37669"]},{"name":"Kingston","zips":["37763"]},{"name":"Kingston Springs","zips":["37082"]},{"name":"Knoxville","zips":["37901","37902","37909","37912","37914","37915","37916","37917","37918","37919","37920","37921","37922","37923","37924","37927","37928","37929","37930","37931","37932","37933","37934","37938","37939","37940","37950","37995","37996","37997","37998"]},{"name":"Kodak","zips":["37764"]},{"name":"Kyles Ford","zips":["37765"]},{"name":"La Follette","zips":["37766"]},{"name":"La Grange","zips":["38046"]},{"name":"La Vergne","zips":["37086","37089"]},{"name":"Laconia","zips":["38045"]},{"name":"Lafayette","zips":["37083"]},{"name":"Lake City","zips":["37769"]},{"name":"Lancaster","zips":["38569"]},{"name":"Lancing","zips":["37770"]},{"name":"Lascassas","zips":["37085"]},{"name":"Laurel Bloomery","zips":["37680"]},{"name":"Lavinia","zips":["38348"]},{"name":"Lawrenceburg","zips":["38464"]},{"name":"Lebanon","zips":["37087","37088","37090"]},{"name":"Lenoir City","zips":["37771","37772"]},{"name":"Lenox","zips":["38047"]},{"name":"Leoma","zips":["38468"]},{"name":"Lewisburg","zips":["37091"]},{"name":"Lexington","zips":["38351"]},{"name":"Liberty","zips":["37095"]},{"name":"Limestone","zips":["37681"]},{"name":"Linden","zips":["37096"]},{"name":"Livingston","zips":["38570"]},{"name":"Lobelville","zips":["37097"]},{"name":"Lone Mountain","zips":["37773"]},{"name":"Lookout Mountain","zips":["37350"]},{"name":"Loretto","zips":["38469"]},{"name":"Loudon","zips":["37774"]},{"name":"Louisville","zips":["37777"]},{"name":"Lowland","zips":["37778"]},{"name":"Lupton City","zips":["37351"]},{"name":"Luray","zips":["38352"]},{"name":"Luttrell","zips":["37779"]},{"name":"Lutts","zips":["38471"]},{"name":"Lyles","zips":["37098"]},{"name":"Lynchburg","zips":["37352"]},{"name":"Lynnville","zips":["38472"]},{"name":"Macon","zips":["38048"]},{"name":"Madison","zips":["37115","37116"]},{"name":"Madisonville","zips":["37354"]},{"name":"Manchester","zips":["37349","37355"]},{"name":"Mansfield","zips":["38236"]},{"name":"Martin","zips":["38237","38238"]},{"name":"Maryville","zips":["37801","37802","37803","37804"]},{"name":"Mascot","zips":["37806"]},{"name":"Mason","zips":["38049"]},{"name":"Maury City","zips":["38050"]},{"name":"Maynardville","zips":["37807"]},{"name":"Mc Donald","zips":["37353"]},{"name":"Mc Ewen","zips":["37101"]},{"name":"Mc Kenzie","zips":["38201"]},{"name":"Mc Lemoresville","zips":["38235"]},{"name":"Mcminnville","zips":["37110","37111"]},{"name":"Medina","zips":["38355"]},{"name":"Medon","zips":["38356"]},{"name":"Mem","zips":["38110"]},{"name":"Memphis","zips":["37501","37544","38101","38103","38104","38105","38106","38107","38108","38109","38111","38112","38113","38114","38115","38116","38117","38118","38119","38120","38122","38124","38125","38126","38127","38128","38130","38131","38132","38133","38134","38135","38136","38137","38141","38145","38147","38148","38150","38151","38152","38157","38159","38161","38163","38165","38166","38167","38168","38173","38174","38175","38177","38181","38182","38184","38186","38187","38188","38190","38193","38194","38197"]},{"name":"Mercer","zips":["38392"]},{"name":"Michie","zips":["38357"]},{"name":"Middleton","zips":["38052"]},{"name":"Midway","zips":["37809"]},{"name":"Milan","zips":["38358"]},{"name":"Milledgeville","zips":["38359"]},{"name":"Milligan College","zips":["37682"]},{"name":"Millington","zips":["38053","38054","38055","38083"]},{"name":"Milton","zips":["37118"]},{"name":"Minor Hill","zips":["38473"]},{"name":"Mitchellville","zips":["37119"]},{"name":"Mohawk","zips":["37810"]},{"name":"Monroe","zips":["38573"]},{"name":"Monteagle","zips":["37356"]},{"name":"Monterey","zips":["38574"]},{"name":"Mooresburg","zips":["37811"]},{"name":"Morris Chapel","zips":["38361"]},{"name":"Morrison","zips":["37357"]},{"name":"Morristown","zips":["37813","37814","37815","37816"]},{"name":"Moscow","zips":["38057"]},{"name":"Mosheim","zips":["37818"]},{"name":"Moss","zips":["38575"]},{"name":"Mount Carmel","zips":["37645"]},{"name":"Mount Juliet","zips":["37121","37122"]},{"name":"Mount Pleasant","zips":["38474"]},{"name":"Mountain City","zips":["37683"]},{"name":"Mountain Home","zips":["37684"]},{"name":"Mphs","zips":["38142"]},{"name":"Mulberry","zips":["37359"]},{"name":"Munford","zips":["38058"]},{"name":"Murfreesboro","zips":["37127","37128","37129","37130","37131","37132","37133"]},{"name":"Nashville","zips":["37201","37202","37203","37204","37205","37206","37207","37208","37209","37210","37211","37212","37213","37214","37215","37216","37217","37218","37219","37220","37221","37222","37224","37227","37228","37229","37230","37232","37234","37235","37236","37238","37240","37241","37242","37243","37244","37246","37250"]},{"name":"Nashvl","zips":["37245","37249"]},{"name":"New Johnsonville","zips":["37134"]},{"name":"New Market","zips":["37820"]},{"name":"New Tazewell","zips":["37824","37825"]},{"name":"Newbern","zips":["38059"]},{"name":"Newcomb","zips":["37819"]},{"name":"Newport","zips":["37821","37822"]},{"name":"Niota","zips":["37826"]},{"name":"Nolensville","zips":["37135"]},{"name":"Norene","zips":["37136"]},{"name":"Normandy","zips":["37360"]},{"name":"Norris","zips":["37828"]},{"name":"Nunnelly","zips":["37137"]},{"name":"Oak Ridge","zips":["37830","37831"]},{"name":"Oakdale","zips":["37829"]},{"name":"Oakfield","zips":["38362"]},{"name":"Oakland","zips":["38060"]},{"name":"Obion","zips":["38240"]},{"name":"Ocoee","zips":["37361"]},{"name":"Old Fort","zips":["37362"]},{"name":"Old Hickory","zips":["37138"]},{"name":"Olivehill","zips":["38475"]},{"name":"Oliver Springs","zips":["37840"]},{"name":"Oneida","zips":["37841"]},{"name":"Only","zips":["37140"]},{"name":"Ooltewah","zips":["37363"]},{"name":"Orlinda","zips":["37141"]},{"name":"Pall Mall","zips":["38577"]},{"name":"Palmer","zips":["37365"]},{"name":"Palmersville","zips":["38241"]},{"name":"Palmyra","zips":["37142"]},{"name":"Paris","zips":["38242"]},{"name":"Parrottsville","zips":["37843"]},{"name":"Parsons","zips":["38363"]},{"name":"Pegram","zips":["37143"]},{"name":"Pelham","zips":["37366"]},{"name":"Petersburg","zips":["37144"]},{"name":"Petros","zips":["37845"]},{"name":"Philadelphia","zips":["37846"]},{"name":"Pickwick Dam","zips":["38365"]},{"name":"Pigeon Forge","zips":["37863","37868"]},{"name":"Pikeville","zips":["37367"]},{"name":"Piney Flats","zips":["37686","37699"]},{"name":"Pinson","zips":["38366"]},{"name":"Pioneer","zips":["37847"]},{"name":"Pleasant Hill","zips":["38578"]},{"name":"Pleasant Shade","zips":["37145"]},{"name":"Pleasant View","zips":["37146"]},{"name":"Pocahontas","zips":["38061"]},{"name":"Portland","zips":["37148"]},{"name":"Powder Springs","zips":["37848"]},{"name":"Powell","zips":["37849"]},{"name":"Primm Springs","zips":["38476"]},{"name":"Prospect","zips":["38477"]},{"name":"Pruden","zips":["37851"]},{"name":"Pulaski","zips":["38478"]},{"name":"Puryear","zips":["38251"]},{"name":"Quebeck","zips":["38579"]},{"name":"Ramer","zips":["38367"]},{"name":"Readyville","zips":["37149"]},{"name":"Reagan","zips":["38368"]},{"name":"Red Boiling Springs","zips":["37150"]},{"name":"Reliance","zips":["37369"]},{"name":"Riceville","zips":["37370"]},{"name":"Rickman","zips":["38580"]},{"name":"Riddleton","zips":["37151"]},{"name":"Ridgely","zips":["38080"]},{"name":"Ridgetop","zips":["37152"]},{"name":"Ripley","zips":["38063"]},{"name":"Rives","zips":["38253"]},{"name":"Roan Mountain","zips":["37687"]},{"name":"Robbins","zips":["37852"]},{"name":"Rock Island","zips":["38581"]},{"name":"Rockford","zips":["37853"]},{"name":"Rockvale","zips":["37153"]},{"name":"Rockwood","zips":["37854"]},{"name":"Rogersville","zips":["37857"]},{"name":"Rossville","zips":["38066"]},{"name":"Rugby","zips":["37733"]},{"name":"Russellville","zips":["37860"]},{"name":"Rutherford","zips":["38369"]},{"name":"Rutledge","zips":["37861"]},{"name":"Saint Joseph","zips":["38481"]},{"name":"Sale Creek","zips":["37373"]},{"name":"Saltillo","zips":["38370"]},{"name":"Samburg","zips":["38254"]},{"name":"Santa Fe","zips":["38482"]},{"name":"Sardis","zips":["38371"]},{"name":"Saulsbury","zips":["38067"]},{"name":"Savannah","zips":["38372"]},{"name":"Scotts Hill","zips":["38374"]},{"name":"Selmer","zips":["38375"]},{"name":"Sequatchie","zips":["37374"]},{"name":"Sevierville","zips":["37862","37864","37876"]},{"name":"Sewanee","zips":["37375","37383"]},{"name":"Seymour","zips":["37865"]},{"name":"Shady Valley","zips":["37688"]},{"name":"Sharon","zips":["38255"]},{"name":"Sharps Chapel","zips":["37866"]},{"name":"Shawanee","zips":["37867"]},{"name":"Shelbyville","zips":["37160","37161","37162"]},{"name":"Sherwood","zips":["37376"]},{"name":"Shiloh","zips":["38376"]},{"name":"Signal Mountain","zips":["37377"]},{"name":"Silerton","zips":["38377"]},{"name":"Silver Point","zips":["38582"]},{"name":"Slayden","zips":["37165"]},{"name":"Smartt","zips":["37378"]},{"name":"Smithville","zips":["37166"]},{"name":"Smyrna","zips":["37167"]},{"name":"Sneedville","zips":["37869"]},{"name":"Soddy Daisy","zips":["37379","37384"]},{"name":"Somerville","zips":["38068"]},{"name":"South Fulton","zips":["38257"]},{"name":"South Pittsburg","zips":["37380"]},{"name":"Southside","zips":["37171"]},{"name":"Sparta","zips":["38583"]},{"name":"Speedwell","zips":["37870"]},{"name":"Spencer","zips":["38585"]},{"name":"Spring City","zips":["37381"]},{"name":"Spring Creek","zips":["38378"]},{"name":"Spring Hill","zips":["37174"]},{"name":"Springfield","zips":["37172"]},{"name":"Springville","zips":["38256"]},{"name":"Stanton","zips":["38069"]},{"name":"Stantonville","zips":["38379"]},{"name":"Stewart","zips":["37175"]},{"name":"Strawberry Plains","zips":["37871"]},{"name":"Sugar Tree","zips":["38380"]},{"name":"Summertown","zips":["38483"]},{"name":"Summitville","zips":["37382"]},{"name":"Sunbright","zips":["37872"]},{"name":"Surgoinsville","zips":["37873"]},{"name":"Sweetwater","zips":["37874"]},{"name":"Taft","zips":["38488"]},{"name":"Talbott","zips":["37877"]},{"name":"Tallassee","zips":["37878"]},{"name":"Tazewell","zips":["37879"]},{"name":"Telford","zips":["37690"]},{"name":"Tellico Plains","zips":["37385"]},{"name":"Ten Mile","zips":["37880"]},{"name":"Tennessee Ridge","zips":["37178"]},{"name":"The Mail Box","zips":["37990"]},{"name":"Thompsons Station","zips":["37179"]},{"name":"Thorn Hill","zips":["37881"]},{"name":"Tigrett","zips":["38070"]},{"name":"Tipton","zips":["38071"]},{"name":"Tiptonville","zips":["38079"]},{"name":"Tn Dept Of Health Environ","zips":["37247"]},{"name":"Tn Dept Of Human Svc","zips":["37248"]},{"name":"Toone","zips":["38381"]},{"name":"Townsend","zips":["37882"]},{"name":"Tracy City","zips":["37387"]},{"name":"Trade","zips":["37691"]},{"name":"Trenton","zips":["38382"]},{"name":"Trezevant","zips":["38258"]},{"name":"Trimble","zips":["38259"]},{"name":"Troy","zips":["38260"]},{"name":"Tullahoma","zips":["37388"]},{"name":"Turtletown","zips":["37391"]},{"name":"Unicoi","zips":["37692"]},{"name":"Union City","zips":["38261","38281"]},{"name":"Unionville","zips":["37180"]},{"name":"Vanleer","zips":["37181"]},{"name":"Viola","zips":["37394"]},{"name":"Vonore","zips":["37885"]},{"name":"Walland","zips":["37886"]},{"name":"Walling","zips":["38587"]},{"name":"Wartburg","zips":["37887"]},{"name":"Wartrace","zips":["37183"]},{"name":"Washburn","zips":["37888"]},{"name":"Watauga","zips":["37694"]},{"name":"Watertown","zips":["37184"]},{"name":"Waverly","zips":["37185"]},{"name":"Waynesboro","zips":["38485"]},{"name":"Westmoreland","zips":["37186"]},{"name":"Westpoint","zips":["38486"]},{"name":"Westport","zips":["38387"]},{"name":"White Bluff","zips":["37187"]},{"name":"White House","zips":["37188"]},{"name":"White Pine","zips":["37890"]},{"name":"Whites Creek","zips":["37189"]},{"name":"Whitesburg","zips":["37891"]},{"name":"Whiteside","zips":["37396"]},{"name":"Whiteville","zips":["38075"]},{"name":"Whitleyville","zips":["38588"]},{"name":"Whitwell","zips":["37397"]},{"name":"Wilder","zips":["38589"]},{"name":"Wildersville","zips":["38388"]},{"name":"Williamsport","zips":["38487"]},{"name":"Williston","zips":["38076"]},{"name":"Winchester","zips":["37398"]},{"name":"Winfield","zips":["37892"]},{"name":"Woodbury","zips":["37190"]},{"name":"Woodland Mills","zips":["38271"]},{"name":"Woodlawn","zips":["37191"]},{"name":"Wynnburg","zips":["38077"]},{"name":"Yorkville","zips":["38389"]},{"name":"Yuma","zips":["38390"]}]}